le_logging/__init__.py
le_logging-0.2.0.dist-info/METADATA
le_logging-0.2.0.dist-info/WHEEL
le_logging-0.2.0.dist-info/entry_points.txt
le_logging-0.2.0.dist-info/top_level.txt
le_logging-0.2.0.dist-info/RECORD
