Metadata-Version: 2.1
Name: le_logging
Version: 0.2.0
Summary: A simple Logging generalizer
Author-email: NoirPi <noirpi@noircoding.de>
Classifier: Programming Language :: Python :: 3
Classifier: Operating System :: OS Independent
Requires-Python: >=3.8
